{
  "project_info": {
    "project_number": "334065327342",
    "project_id": "fir-login-auth-64711",
    "storage_bucket": "fir-login-auth-64711.appspot.com"
  },
  "client": [
    {
      "client_info": {
        "mobilesdk_app_id": "1:334065327342:android:288632794a418a061c67ff",
        "android_client_info": {
          "package_name": "com.biswesh.a15_firebaselogin_auth"
        }
      },
      "oauth_client": [],
      "api_key": [
        {
          "current_key": "AIzaSyB0Sxv1Gu10PfOrqoJy3TaVNX9cqR08_CU"
        }
      ],
      "services": {
        "appinvite_service": {
          "other_platform_oauth_client": []
        }
      }
    }
  ],
  "configuration_version": "1"
}